nofakes.py
nofakes-0.0.1.dist-info/LICENSE
nofakes-0.0.1.dist-info/METADATA
nofakes-0.0.1.dist-info/WHEEL
nofakes-0.0.1.dist-info/top_level.txt
nofakes-0.0.1.dist-info/RECORD
